doc_master/__init__.py
doc_master/main.py
doc_master-0.0.2.dist-info/LICENSE
doc_master-0.0.2.dist-info/METADATA
doc_master-0.0.2.dist-info/WHEEL
doc_master-0.0.2.dist-info/RECORD
