Metadata-Version: 2.1
Name: doc-master
Version: 0.0.2
Summary: Paper - Pytorch
Home-page: https://github.com/The-Swarm-Corporation/doc-master
License: MIT
Keywords: document,reader,file,content,extraction,pdf,docx,excel
Author: Kye Gomez
Author-email: kye@apac.ai
Requires-Python: >=3.10,<4.0
Classifier: Development Status :: 4 - Beta
Classifier: Intended Audience :: Developers
Classifier: License :: OSI Approved :: MIT License
Classifier: Programming Language :: Python :: 3
Classifier: Programming Language :: Python :: 3.10
Classifier: Programming Language :: Python :: 3.11
Classifier: Programming Language :: Python :: 3.12
Classifier: Programming Language :: Python :: 3.9
Classifier: Topic :: Scientific/Engineering :: Artificial Intelligence
Requires-Dist: Pillow
Requires-Dist: PyYAML
Requires-Dist: chardet
Requires-Dist: loguru
Requires-Dist: pandas
Requires-Dist: pypdf
Requires-Dist: pytesseract
Requires-Dist: python-docx
Requires-Dist: python-magic
Project-URL: Documentation, https://github.com/The-Swarm-Corporation/doc-master
Project-URL: Repository, https://github.com/The-Swarm-Corporation/doc-master
